<?xml version="1.0" encoding="UTF-8"?>
<objects serializationModel="Studio.02.02.00">
	<object class="AudioFile" id="{07d1245f-32a3-4fc3-b707-7a13ea9c368f}">
		<property name="assetPath">
			<value>ItemSound/armor_bone_2.wav</value>
		</property>
		<property name="frequencyInKHz">
			<value>22.0499992</value>
		</property>
		<property name="channelCount">
			<value>1</value>
		</property>
		<property name="length">
			<value>0.58757369614512467</value>
		</property>
		<relationship name="masterAssetFolder">
			<destination>{65641f76-d24d-4b0d-abbe-f1b29b598cec}</destination>
		</relationship>
	</object>
</objects>
