<?xml version="1.0" encoding="UTF-8"?>
<objects serializationModel="Studio.02.02.00">
	<object class="AudioFile" id="{0eb43d7d-1016-423e-a8a2-20ee4c31472c}">
		<property name="assetPath">
			<value>AmbSound/AmbSound/ad_bird_22.wav</value>
		</property>
		<property name="frequencyInKHz">
			<value>22.0499992</value>
		</property>
		<property name="channelCount">
			<value>1</value>
		</property>
		<property name="length">
			<value>3.9937868480725625</value>
		</property>
		<relationship name="masterAssetFolder">
			<destination>{65641f76-d24d-4b0d-abbe-f1b29b598cec}</destination>
		</relationship>
	</object>
</objects>
