<?xml version="1.0" encoding="UTF-8"?>
<objects serializationModel="Studio.02.02.00">
	<object class="AudioFile" id="{78f409fb-4787-453a-b7aa-0b01acb9c7b7}">
		<property name="assetPath">
			<value>MonSound/cat_the_cat/catthecat_step_1.wav</value>
		</property>
		<property name="frequencyInKHz">
			<value>22.0499992</value>
		</property>
		<property name="channelCount">
			<value>1</value>
		</property>
		<property name="length">
			<value>0.24684807256235827</value>
		</property>
		<relationship name="masterAssetFolder">
			<destination>{65641f76-d24d-4b0d-abbe-f1b29b598cec}</destination>
		</relationship>
	</object>
</objects>
